CHANGES.txt
buildout.cfg
setup.py
src/zc/__init__.py
src/zc.recipe.wrapper.egg-info/PKG-INFO
src/zc.recipe.wrapper.egg-info/SOURCES.txt
src/zc.recipe.wrapper.egg-info/dependency_links.txt
src/zc.recipe.wrapper.egg-info/entry_points.txt
src/zc.recipe.wrapper.egg-info/namespace_packages.txt
src/zc.recipe.wrapper.egg-info/not-zip-safe
src/zc.recipe.wrapper.egg-info/requires.txt
src/zc.recipe.wrapper.egg-info/top_level.txt
src/zc/recipe/__init__.py
src/zc/recipe/wrapper/README.txt
src/zc/recipe/wrapper/__init__.py
src/zc/recipe/wrapper/tests.py