Metadata-Version: 1.0
Name: zc.recipe.wrapper
Version: 1.1.0
Summary: Recipe that creates shell wrapper scripts
Home-page: UNKNOWN
Author: Aaron Lehmann
Author-email: aaron@zope.com
License: ZPL 2.1
Keywords: development build wrapper generater
Platform: UNKNOWN
Classifier: Framework :: Buildout
Classifier: Intended Audience :: Developers
Classifier: License :: OSI Approved :: Zope Public License
Classifier: Topic :: Software Development :: Build Tools
Classifier: Topic :: Software Development :: Libraries :: Python Modules
